{
  "schema_version": 1,
  "netuid": 57,
  "name": "Sparket",
  "slug": "sn-57",
  "status": "active",
  "categories": [
    "baseline-curated",
    "identity-reviewed",
    "official-source-repo",
    "official-website",
    "prediction-market",
    "sports"
  ],
  "website_url": "https://sparket.ai/",
  "source_repo": "https://github.com/sparket-ai/sparket-ai",
  "dashboard_url": "https://taomarketcap.com/subnets/57",
  "notes": "Reviewed overlay for SN57 using the official Sparket website and source repository. No official docs/API/OpenAPI surface is verified yet.",
  "curation": {
    "level": "maintainer-reviewed",
    "review_state": "maintainer-reviewed",
    "reviewed_at": "2026-06-08T10:35:00.000Z",
    "verified_at": "2026-06-08T10:35:00.000Z",
    "source_count": 4,
    "gap_notes": [
      "No verified official docs URL yet.",
      "No verified safe public subnet API endpoint yet.",
      "No verified OpenAPI/Swagger schema yet.",
      "No verified SSE/event stream yet.",
      "No verified standalone static data artifact yet."
    ]
  },
  "surfaces": [
    {
      "id": "sn-57-sparket-website",
      "name": "Sparket website",
      "kind": "website",
      "url": "https://sparket.ai/",
      "provider": "sparket",
      "auth_required": false,
      "authority": "official",
      "public_safe": true,
      "source_urls": ["https://sparket.ai/"],
      "probe": {
        "enabled": true,
        "method": "HEAD",
        "expect": "html",
        "timeout_ms": 10000
      },
      "notes": "Official Sparket website."
    },
    {
      "id": "sn-57-sparket-source",
      "name": "Sparket source repository",
      "kind": "source-repo",
      "url": "https://github.com/sparket-ai/sparket-ai",
      "provider": "sparket",
      "auth_required": false,
      "authority": "official",
      "public_safe": true,
      "source_urls": [
        "https://api.github.com/repos/sparket-ai/sparket-ai",
        "https://github.com/sparket-ai/sparket-ai"
      ],
      "probe": {
        "enabled": true,
        "method": "HEAD",
        "expect": "any",
        "timeout_ms": 10000
      },
      "notes": "Official Sparket source repository."
    },
    {
      "id": "sn-57-sparket-subnet-api",
      "name": "Sparket API health",
      "kind": "subnet-api",
      "url": "https://sparket.ai/api/v1/health",
      "provider": "sparket",
      "auth_required": false,
      "authority": "community",
      "public_safe": true,
      "source_urls": ["https://sparket.ai/"],
      "probe": {
        "enabled": true,
        "method": "GET",
        "expect": "json",
        "timeout_ms": 10000
      },
      "review": {
        "state": "community-submitted",
        "submitted_by": "nickmopen"
      },
      "notes": "Public no-auth GET returning the Sparket (SN57) backend API health as JSON (status, db connectivity, version, and sync lag). Served on the subnet's own registered website domain sparket.ai under /api/v1/. Fills the file's noted missing public-API-endpoint gap."
    }
  ]
}
