{
  "categories": [
    "baseline-curated"
  ],
  "curation": {
    "gap_notes": [
      "No verified OpenAPI/Swagger surface yet.",
      "No verified subnet API surface yet.",
      "No verified SSE/event stream yet.",
      "No verified data artifact yet."
    ],
    "level": "machine-verified",
    "review_state": "machine-generated",
    "reviewed_at": null,
    "source_count": 3,
    "verified_at": null
  },
  "dashboard_url": "https://taomarketcap.com/subnets/13",
  "docs_url": "https://ico.org.uk/for-organisations/uk-gdpr-guidance-and-resources/lawful-basis/a-guide-to-lawful-basis",
  "links": [],
  "name": "Data Universe",
  "netuid": 13,
  "notes": "Machine-generated baseline overlay from verified public-source candidates.",
  "schema_version": 1,
  "slug": "sn-13",
  "source_repo": "https://github.com/macrocosm-os/data-universe",
  "status": "active",
  "surfaces": [
    {
      "auth_required": false,
      "authority": "registry-observed",
      "id": "sn-13-taomarketcap-source-repo",
      "kind": "source-repo",
      "name": "Data Universe source repository",
      "notes": "Discovered from TaoMarketCap subnet identity metadata. Not probed or verified by Metagraphed.",
      "probe": {
        "enabled": true,
        "expect": "any",
        "method": "HEAD",
        "timeout_ms": 10000
      },
      "provider": "taomarketcap",
      "public_safe": true,
      "quality_signals": {
        "archived": false,
        "has_default_branch": true,
        "has_recent_push_metadata": true,
        "public_safe": true,
        "source_tier": "third-party-index"
      },
      "rate_limit_notes": "Candidate only; no recurring probe is configured until maintainer review.",
      "source_urls": [
        "https://api.taomarketcap.com/public/v1/subnets/13",
        "https://github.com/tensorplex-labs/subnet-docs/blob/main/data/13/subnet.json"
      ],
      "url": "https://github.com/macrocosm-os/data-universe"
    },
    {
      "auth_required": false,
      "authority": "registry-observed",
      "id": "sn-13-taomarketcap-website",
      "kind": "website",
      "name": "Data Universe website",
      "notes": "Discovered from TaoMarketCap subnet identity metadata. Not probed or verified by Metagraphed.",
      "probe": {
        "enabled": true,
        "expect": "any",
        "method": "HEAD",
        "timeout_ms": 10000
      },
      "provider": "taomarketcap",
      "public_safe": true,
      "quality_signals": {
        "content_type_matches_kind": true,
        "public_safe": true,
        "rate_limited": false,
        "redirected": true,
        "source_tier": "third-party-index",
        "transient_failure": false
      },
      "rate_limit_notes": "Candidate only; no recurring probe is configured until maintainer review.",
      "source_urls": [
        "https://api.taomarketcap.com/public/v1/subnets/13"
      ],
      "url": "https://www.macrocosmos.ai/gravity"
    },
    {
      "auth_required": false,
      "authority": "registry-observed",
      "id": "sn-13-github-readme-macrocosm-os-data-universe-docs-1",
      "kind": "docs",
      "name": "Data Universe docs",
      "notes": "Discovered from a public GitHub README link. Requires verification before promotion.",
      "probe": {
        "enabled": true,
        "expect": "any",
        "method": "HEAD",
        "timeout_ms": 10000
      },
      "provider": "taomarketcap",
      "public_safe": true,
      "quality_signals": {
        "content_type_matches_kind": true,
        "public_safe": true,
        "rate_limited": false,
        "redirected": false,
        "source_tier": "community-docs",
        "transient_failure": false
      },
      "rate_limit_notes": "Candidate only; no recurring probe is configured until maintainer review.",
      "source_urls": [
        "https://github.com/macrocosm-os/data-universe/blob/main/README.md"
      ],
      "url": "https://ico.org.uk/for-organisations/uk-gdpr-guidance-and-resources/lawful-basis/a-guide-to-lawful-basis"
    },
    {
      "auth_required": false,
      "authority": "registry-observed",
      "id": "sn-13-github-readme-macrocosm-os-data-universe-docs-2",
      "kind": "docs",
      "name": "Data Universe docs",
      "notes": "Discovered from a public GitHub README link. Requires verification before promotion.",
      "probe": {
        "enabled": true,
        "expect": "any",
        "method": "HEAD",
        "timeout_ms": 10000
      },
      "provider": "taomarketcap",
      "public_safe": true,
      "quality_signals": {
        "content_type_matches_kind": true,
        "public_safe": true,
        "rate_limited": false,
        "redirected": false,
        "source_tier": "community-docs",
        "transient_failure": false
      },
      "rate_limit_notes": "Candidate only; no recurring probe is configured until maintainer review.",
      "source_urls": [
        "https://github.com/macrocosm-os/data-universe/blob/main/README.md"
      ],
      "url": "https://ico.org.uk/for-organisations/uk-gdpr-guidance-and-resources/individual-rights/individual-rights"
    },
    {
      "auth_required": false,
      "authority": "registry-observed",
      "id": "sn-13-github-readme-macrocosm-os-data-universe-docs-3",
      "kind": "docs",
      "name": "Data Universe docs",
      "notes": "Discovered from a public GitHub README link. Requires verification before promotion.",
      "probe": {
        "enabled": true,
        "expect": "any",
        "method": "HEAD",
        "timeout_ms": 10000
      },
      "provider": "taomarketcap",
      "public_safe": true,
      "quality_signals": {
        "content_type_matches_kind": true,
        "public_safe": true,
        "rate_limited": false,
        "redirected": false,
        "source_tier": "community-docs",
        "transient_failure": false
      },
      "rate_limit_notes": "Candidate only; no recurring probe is configured until maintainer review.",
      "source_urls": [
        "https://github.com/macrocosm-os/data-universe/blob/main/README.md"
      ],
      "url": "https://ico.org.uk/for-organisations/uk-gdpr-guidance-and-resources/security/a-guide-to-data-security"
    },
    {
      "auth_required": false,
      "authority": "registry-observed",
      "id": "sn-13-github-readme-macrocosm-os-data-universe-docs-4",
      "kind": "docs",
      "name": "Data Universe docs",
      "notes": "Discovered from a public GitHub README link. Requires verification before promotion.",
      "probe": {
        "enabled": true,
        "expect": "any",
        "method": "HEAD",
        "timeout_ms": 10000
      },
      "provider": "taomarketcap",
      "public_safe": true,
      "quality_signals": {
        "content_type_matches_kind": true,
        "public_safe": true,
        "rate_limited": false,
        "redirected": false,
        "source_tier": "community-docs",
        "transient_failure": false
      },
      "rate_limit_notes": "Candidate only; no recurring probe is configured until maintainer review.",
      "source_urls": [
        "https://github.com/macrocosm-os/data-universe/blob/main/README.md"
      ],
      "url": "https://ico.org.uk/for-organisations/report-a-breach/personal-data-breach/personal-data-breaches-a-guide"
    },
    {
      "auth_required": false,
      "authority": "registry-observed",
      "id": "sn-13-taomarketcap-dashboard",
      "kind": "dashboard",
      "name": "Data Universe TaoMarketCap dashboard",
      "notes": "Universal TaoMarketCap subnet dashboard candidate. Third-party enrichment, not protocol authority.",
      "probe": {
        "enabled": true,
        "expect": "any",
        "method": "HEAD",
        "timeout_ms": 10000
      },
      "provider": "taomarketcap",
      "public_safe": true,
      "quality_signals": {
        "content_type_matches_kind": true,
        "public_safe": true,
        "rate_limited": false,
        "redirected": false,
        "source_tier": "third-party-index",
        "transient_failure": false
      },
      "rate_limit_notes": "Candidate only; no recurring probe is configured until maintainer review.",
      "source_urls": [
        "https://api.taomarketcap.com/public/v1/subnets/13"
      ],
      "url": "https://taomarketcap.com/subnets/13"
    }
  ],
  "website_url": "https://www.macrocosmos.ai/gravity"
}
